README.md
bunnystats.py
pyproject.toml
bunnystats.egg-info/PKG-INFO
bunnystats.egg-info/SOURCES.txt
bunnystats.egg-info/dependency_links.txt
bunnystats.egg-info/requires.txt
bunnystats.egg-info/top_level.txt