Metadata-Version: 2.4
Name: bunnystats
Version: 1.0
Summary: A Python library for obtaining usage statistics for the bunny.net CDN
Author: Michael Herrmann
License-Expression: MIT
Project-URL: Homepage, https://github.com/mherrmann/bunnystats
Classifier: Development Status :: 3 - Alpha
Classifier: Intended Audience :: Developers
Classifier: Programming Language :: Python :: 3
Classifier: Programming Language :: Python :: 3.8
Classifier: Programming Language :: Python :: 3.9
Classifier: Programming Language :: Python :: 3.10
Classifier: Programming Language :: Python :: 3.11
Classifier: Programming Language :: Python :: 3.12
Requires-Python: >=3.8
Requires-Dist: requests
